setup.cfg
setup.py
chunky/__init__.py
chunky.egg-info/PKG-INFO
chunky.egg-info/SOURCES.txt
chunky.egg-info/dependency_links.txt
chunky.egg-info/pbr.json
chunky.egg-info/top_level.txt