Metadata-Version: 1.1
Name: chunky
Version: 0.5.1
Summary: A python module to handle reading and writing of text files in chunks.
Home-page: http://github.com/kapilratnani/chunky
Author: Kapil Ratnani
Author-email: kapil.ratnani@iiitb.net
License: UNKNOWN
Download-URL: http://github.com/kapilratnani/chunky/tarball/0.5.1
Keywords: chunk,parts,files,chunks,split
Platform: UNKNOWN
